{"title": "Legal Notice", "byline": null, "dir": null, "lang": "en", "content": "<div id=\"readability-page-1\" class=\"page\"><div>\n<p><strong>1. WEBSITE PRESENTATION</strong>\n*Owner : BSPORT \u2013 30/32 boulevard de S\u00e9bastopol, 75004 Paris\u2013 France<br>\n<!-- -->Creator : Agence la Cocotte<br>\n<!-- -->Publication manager : marketing@bsport.io\nWebmaster : marketing@bsport.io\nCustomer Service: support@bsport.io</p>\n<p><strong>2. TERMS AND CONDITIONS OF WEBSITE USE AND OFFERED SERVICES</strong><br>\n<em>By using the pro.bsport.io website, the user is deemed to have implicitly and unreservedly agreed to these terms and conditions of use. These terms and conditions of use may be modified or supplemented at any time. Users of the pro.bsport.io website should regularly review these terms and conditions.</em></p>\n<p><em>The website is normally available to users at all times. Nonetheless,BSPORT may decide to prevent access to perform technical maintenance, in which case every effort will be made to notify users in advance of the time and date of the interruption.</em></p>\n<p><em>BSPORT updates the pro.bsport.io website on a regular basis. The legal notice may also be modified at any time. It will be binding on the user, who should regularly read the legal notice in order to be aware of any changes.</em></p>\n<p><strong>3. DESCRIPTION OF PROVIDED SERVICES</strong><br>\n<em>The purpose of the pro.bsport.io website is to provide information about the company\u2019s activities.</em></p>\n<p><em>BSPORT endeavours to provide precise information on the pro.bsport.io website insofar as possible. However, it may not be held liable for any omissions, inaccuracies or lack of updates whether of its own doing or of that of partner third parties providing the information concerned.</em></p>\n<p><em>All information given on pro.bsport.io is for reference purposes only and is subject to modifications. Moreover, the information on pro.bsport.io is not exhaustive and may undergo changes after being placed online.</em></p>\n<p><strong>4. CONTRACTUAL LIMITS ON TECHNICAL ASPECTS</strong><br>\n<em>This website uses WordPress technology.<br>\n<!-- -->The website may not be held liable for any material damages linked to its use. The website user agrees to access the website using modern equipment that does not contain any viruses and with an up-to-date web browser.</em></p>\n<p><strong>5. INTELLECTUAL PROPERTY AND BREACHES</strong><br>\n<em>BSPORT is the owner of the intellectual property and usage rights pertaining to all elements accessible on the website, including texts, images, graphics, logos, icons, audio and software.</em></p>\n<p><em>Except where authorised in writing beforehand by BSPORT, it is prohibited to reproduce, depict, modify, publish or adapt any element of the website, in whole or in part, regardless of the means or procedure used.</em></p>\n<p><em>Any unauthorised exploitation of the website or of an element contained therein will constitute an infringement of intellectual property rights and will be prosecuted in accordance with Articles L.335-2 et seq. of the French Intellectual Property Code.</em></p>\n<p><strong>6. LIABILITY DISCLAIMER</strong><br>\n<em>BSPORT may not be held liable for any direct or indirect damages caused to the user\u2019s equipment during access to the pro.bsport.io website and resulting from either the use of equipment not fulfilling the specifications set out in point 4 above or the occurrence of a bug or incompatibility.</em></p>\n<p><em>Furthermore, BSPORT may not be held liable for any indirect damages ensuing from the use of the pro.bsport.io website.</em></p>\n<p><strong>7. MANAGEMENT OF PERSONAL DATA</strong><br>\n<em>BSPORT does not store the personal data of users who connect to the pro.bsport.io website.</em></p>\n<p><strong>8. HYPERTEXT LINKS AND COOKIES</strong><br>\n<em>When browsing the pro.bsport.io website, cookies may be installed on the user\u2019s computer. A cookie is a small text file. It does not identify the user but it records information relating to the user\u2019s browsing of a website. The data obtained is used to facilitate subsequent browsing of the website and enable various measurements of visit frequency.</em></p>\n<p><em>The pro.bsport.io website uses analytical cookies.</em></p>\n<p><em>However, the user may change the settings of the computer to reject cookies as follows:</em></p>\n<p><em>On Internet Explorer: Select the tools button (gear cog icon on upper right) / \u2018Internet options\u2019. Click \u2018Privacy\u2019 and select \u2018Block all cookies\u2019. Click Ok.</em></p>\n<p><em>On Firefox: at the top of the browser, click the menu button and go to \u2018Options\u2019. Select \u2018Privacy and security\u2019. Set \u2018Firefox will choose:\u2019 to \u2018Use custom settings for history\u2019. Uncheck cookies to deactivate them.</em></p>\n<p><em>On Safari: Click on the menu icon at the top-right of the browser (gear cog symbol). Select \u2018Preferences\u2019. Click \u2018Display advanced settings\u2019. In the \u2018Privacy\u2019 section, click on \u2018Content settings\u2019. Under \u2018Cookies\u2019, you can choose to block cookies.</em></p>\n<p><em>Google Analytics cookies</em></p>\n<p><em>The data collected by means of the cookies deposited by this blog are collected by Google Analytics. You can see here the privacy policy of Google Analytics. If you want to see in detail the uses of Google Analytics Cookies.</em></p>\n<p>*The cookies installed by Google Analytics:<br>\n<em>_ga</em>\n<em>_gat</em></p>\n<p><strong>9. APPLICABLE LAW AND JURISDICTION</strong><br>\n<em>Any dispute in relation to the use of the pro.bsport.io website is subject to French law. The competent courts of Paris shall have exclusive jurisdiction to hear such disputes.</em></p>\n<p><strong>10. PRINCIPAL LEGISLATION</strong><br>\n<em>Law no. 78-17 of 6 January 1978, as amended by Law no. 2004-801 of 6 August 2004, on computer technology, files and freedoms.</em></p>\n<p><em>Law no. 2004-575 of 21 June 2004 on enhancing confidence in the digital economy.</em></p>\n<p><strong>11. GLOSSARY</strong><br>\n<!-- -->*User: a person who connects to and browses the above-mentioned website. *\n<em>Personal data: \u201cinformation of any form that allows the direct or indirect identification of a natural person to whom the data refers\u201d (Article 4 of Law no. 78-17 of 6 January 1978).</em></p></div></div>", "textContent": "\n1. WEBSITE PRESENTATION\n*Owner : BSPORT \u2013 30/32 boulevard de S\u00e9bastopol, 75004 Paris\u2013 France\nCreator : Agence la Cocotte\nPublication manager : marketing@bsport.io\nWebmaster : marketing@bsport.io\nCustomer Service: support@bsport.io\n2. TERMS AND CONDITIONS OF WEBSITE USE AND OFFERED SERVICES\nBy using the pro.bsport.io website, the user is deemed to have implicitly and unreservedly agreed to these terms and conditions of use. These terms and conditions of use may be modified or supplemented at any time. Users of the pro.bsport.io website should regularly review these terms and conditions.\nThe website is normally available to users at all times. Nonetheless,BSPORT may decide to prevent access to perform technical maintenance, in which case every effort will be made to notify users in advance of the time and date of the interruption.\nBSPORT updates the pro.bsport.io website on a regular basis. The legal notice may also be modified at any time. It will be binding on the user, who should regularly read the legal notice in order to be aware of any changes.\n3. DESCRIPTION OF PROVIDED SERVICES\nThe purpose of the pro.bsport.io website is to provide information about the company\u2019s activities.\nBSPORT endeavours to provide precise information on the pro.bsport.io website insofar as possible. However, it may not be held liable for any omissions, inaccuracies or lack of updates whether of its own doing or of that of partner third parties providing the information concerned.\nAll information given on pro.bsport.io is for reference purposes only and is subject to modifications. Moreover, the information on pro.bsport.io is not exhaustive and may undergo changes after being placed online.\n4. CONTRACTUAL LIMITS ON TECHNICAL ASPECTS\nThis website uses WordPress technology.\nThe website may not be held liable for any material damages linked to its use. The website user agrees to access the website using modern equipment that does not contain any viruses and with an up-to-date web browser.\n5. INTELLECTUAL PROPERTY AND BREACHES\nBSPORT is the owner of the intellectual property and usage rights pertaining to all elements accessible on the website, including texts, images, graphics, logos, icons, audio and software.\nExcept where authorised in writing beforehand by BSPORT, it is prohibited to reproduce, depict, modify, publish or adapt any element of the website, in whole or in part, regardless of the means or procedure used.\nAny unauthorised exploitation of the website or of an element contained therein will constitute an infringement of intellectual property rights and will be prosecuted in accordance with Articles L.335-2 et seq. of the French Intellectual Property Code.\n6. LIABILITY DISCLAIMER\nBSPORT may not be held liable for any direct or indirect damages caused to the user\u2019s equipment during access to the pro.bsport.io website and resulting from either the use of equipment not fulfilling the specifications set out in point 4 above or the occurrence of a bug or incompatibility.\nFurthermore, BSPORT may not be held liable for any indirect damages ensuing from the use of the pro.bsport.io website.\n7. MANAGEMENT OF PERSONAL DATA\nBSPORT does not store the personal data of users who connect to the pro.bsport.io website.\n8. HYPERTEXT LINKS AND COOKIES\nWhen browsing the pro.bsport.io website, cookies may be installed on the user\u2019s computer. A cookie is a small text file. It does not identify the user but it records information relating to the user\u2019s browsing of a website. The data obtained is used to facilitate subsequent browsing of the website and enable various measurements of visit frequency.\nThe pro.bsport.io website uses analytical cookies.\nHowever, the user may change the settings of the computer to reject cookies as follows:\nOn Internet Explorer: Select the tools button (gear cog icon on upper right) / \u2018Internet options\u2019. Click \u2018Privacy\u2019 and select \u2018Block all cookies\u2019. Click Ok.\nOn Firefox: at the top of the browser, click the menu button and go to \u2018Options\u2019. Select \u2018Privacy and security\u2019. Set \u2018Firefox will choose:\u2019 to \u2018Use custom settings for history\u2019. Uncheck cookies to deactivate them.\nOn Safari: Click on the menu icon at the top-right of the browser (gear cog symbol). Select \u2018Preferences\u2019. Click \u2018Display advanced settings\u2019. In the \u2018Privacy\u2019 section, click on \u2018Content settings\u2019. Under \u2018Cookies\u2019, you can choose to block cookies.\nGoogle Analytics cookies\nThe data collected by means of the cookies deposited by this blog are collected by Google Analytics. You can see here the privacy policy of Google Analytics. If you want to see in detail the uses of Google Analytics Cookies.\n*The cookies installed by Google Analytics:\n_ga\n_gat\n9. APPLICABLE LAW AND JURISDICTION\nAny dispute in relation to the use of the pro.bsport.io website is subject to French law. The competent courts of Paris shall have exclusive jurisdiction to hear such disputes.\n10. PRINCIPAL LEGISLATION\nLaw no. 78-17 of 6 January 1978, as amended by Law no. 2004-801 of 6 August 2004, on computer technology, files and freedoms.\nLaw no. 2004-575 of 21 June 2004 on enhancing confidence in the digital economy.\n11. GLOSSARY\n*User: a person who connects to and browses the above-mentioned website. *\nPersonal data: \u201cinformation of any form that allows the direct or indirect identification of a natural person to whom the data refers\u201d (Article 4 of Law no. 78-17 of 6 January 1978).", "length": 5407, "excerpt": "Terms & Conditions", "siteName": "Legal Notice", "applied": false}